.gitignore
LICENSE
MANIFEST.in
README.md
pyproject.toml
requirements.txt
requirements_dev.txt
setup.cfg
setup.py
tml_assignment.pdf
tox.ini
.github/workflows/tests.yml
src/__init__.py
src/ggg_delauny_final.png
src/gng_final.png
src/graph_finding.py
src/mapper_final.png
src/mapper_final_dist_to_mean.png
src/mapper_final_projection.png
src/persistent_homology.py
src/project.ipynb
src/py.typed
src/reeb_graphs.py
src/som_final.png
src/topological_autoencoder_final.png
src/topological_neural_networks.py
src/utils.py
src/INF367_chen.egg-info/PKG-INFO
src/INF367_chen.egg-info/SOURCES.txt
src/INF367_chen.egg-info/dependency_links.txt
src/INF367_chen.egg-info/not-zip-safe
src/INF367_chen.egg-info/requires.txt
src/INF367_chen.egg-info/top_level.txt