Metadata-Version: 2.1
Name: INF367-chen
Version: 1.1.1
Summary: Course project for INF367
Home-page: https://github.com/I-HaoChen/INF367A
Author: I-Hao Chen
Author-email: i-hao.chen@live.de
License: GNU GENERAL PUBLIC LICENSE
Platform: unix
Platform: linux
Platform: osx
Platform: cygwin
Platform: win32
Classifier: Programming Language :: Python :: 3
Classifier: Programming Language :: Python :: 3 :: Only
Classifier: Programming Language :: Python :: 3.8
Classifier: Programming Language :: Python :: 3.9
Requires-Python: >=3.8
Provides-Extra: testing
License-File: LICENSE
